README.md
setup.py
SecuenciaAlfanumerica/SecuenciaAlfanumerica.py
SecuenciaAlfanumerica/__init__.py
SecuenciaAlfanumerica.egg-info/PKG-INFO
SecuenciaAlfanumerica.egg-info/SOURCES.txt
SecuenciaAlfanumerica.egg-info/dependency_links.txt
SecuenciaAlfanumerica.egg-info/top_level.txt