Metadata-Version: 2.1
Name: SecuenciaAlfanumerica
Version: 2022.5.10
Summary: Convierte de un número o números a un grupo de caracteres y viceversa
Home-page: https://github.com/Xaival/Libreria-Python-Secuencia-alfanumerica
Author: Xaival
Author-email: xaival.dark@gmail.com
License: MIT
Keywords: conversions,sequence,alphanumeric,binary
Platform: UNKNOWN
